sargilo/__init__.py
sargilo/collection.py
sargilo/dataset.py
sargilo/integrations/__init__.py
sargilo/integrations/base.py
sargilo/integrations/django_integration.py
sargilo/item.py
sargilo/relations.py
sargilo/schema.py
sargilo/tests/__init__.py
sargilo/tests/blog/__init__.py
sargilo/tests/blog/apps.py
sargilo/tests/blog/migrations/0001_initial.py
sargilo/tests/blog/migrations/__init__.py
sargilo/tests/blog/models.py
sargilo/tests/blog/south_migrations/0001_initial.py
sargilo/tests/blog/south_migrations/0002_auto__chg_field_post_critique.py
sargilo/tests/blog/south_migrations/__init__.py
sargilo/tests/blog/tests/__init__.py
sargilo/tests/blog/tests/compatibility.py
sargilo/tests/blog/tests/dataset.yaml
sargilo/tests/blog/tests/schema.json
sargilo/tests/blog/tests/test_configuration.py
sargilo/tests/blog/tests/test_creation.py
sargilo/tests/blog/tests/test_django_integration.py
sargilo/tests/blog/tests/test_schema.py
sargilo/tests/blog/views.py
sargilo/tests/django111_test_project/Dockerfile
sargilo/tests/django111_test_project/__init__.py
sargilo/tests/django111_test_project/manage.py
sargilo/tests/django111_test_project/pyproject.toml
sargilo/tests/django111_test_project/settings.py
sargilo/tests/django111_test_project/urls.py
sargilo/tests/django14_test_project/Dockerfile
sargilo/tests/django14_test_project/__init__.py
sargilo/tests/django14_test_project/manage.py
sargilo/tests/django14_test_project/pyproject.toml
sargilo/tests/django14_test_project/settings.py
sargilo/tests/django14_test_project/urls.py
sargilo/tests/django18_test_project/Dockerfile
sargilo/tests/django18_test_project/__init__.py
sargilo/tests/django18_test_project/manage.py
sargilo/tests/django18_test_project/pyproject.toml
sargilo/tests/django18_test_project/settings.py
sargilo/tests/django18_test_project/urls.py
sargilo/tests/django22_test_project/Dockerfile
sargilo/tests/django22_test_project/__init__.py
sargilo/tests/django22_test_project/manage.py
sargilo-0.1.7.dist-info/WHEEL
sargilo-0.1.7.dist-info/METADATA
sargilo-0.1.7.dist-info/RECORD
