Metadata-Version: 2.1
Name: sargilo
Version: 0.1.7
Summary: 💾 Data loader for Humans
Home-page: https://github.com/nick-lehmann/Sargilo
License: MIT
Keywords: testing,data,mocking
Author: Nick Lehmann
Author-email: nick@lehmann.sh
Requires-Python: >=2.7
Classifier: Development Status :: 2 - Pre-Alpha
Classifier: Framework :: Django
Classifier: Intended Audience :: Developers
Classifier: License :: OSI Approved :: MIT License
Classifier: Programming Language :: Python :: 2
Classifier: Programming Language :: Python :: 2.7
Classifier: Programming Language :: Python :: 3
Classifier: Programming Language :: Python :: 3.4
Classifier: Programming Language :: Python :: 3.5
Classifier: Programming Language :: Python :: 3.6
Classifier: Programming Language :: Python :: 3.7
Classifier: Programming Language :: Python :: 3.8
Classifier: Topic :: Database
Classifier: Topic :: Software Development :: Testing
Classifier: Topic :: Software Development :: Testing :: BDD
Classifier: Topic :: Software Development :: Testing :: Mocking
Provides-Extra: docs
Requires-Dist: ruamel.yaml
Requires-Dist: typing
Project-URL: Bug Tracker, https://github.com/nick-lehmann/Sargilo/issues
Project-URL: Documentation, https://testo.nicklehmann.sh
Project-URL: Repository, https://github.com/nick-lehmann/Sargilo
